heishamon_rules_minify/__init__.py
heishamon_rules_minify/__main__.py
heishamon_rules_minify/_version.py
heishamon_rules_minify/cli.py
heishamon_rules_minify/minifier.py
heishamon_rules_minify-0.0.4.dist-info/LICENSE
heishamon_rules_minify-0.0.4.dist-info/METADATA
heishamon_rules_minify-0.0.4.dist-info/WHEEL
heishamon_rules_minify-0.0.4.dist-info/entry_points.txt
heishamon_rules_minify-0.0.4.dist-info/top_level.txt
heishamon_rules_minify-0.0.4.dist-info/RECORD
