Metadata-Version: 2.1
Name: heishamon_rules_minify
Version: 0.0.4
Summary: A Python CLI to minify Heishamon rules
Author: Klaas Hoekstra
Author-email: klaas.hoekstra94@gmail.com
Maintainer: Klaas Hoekstra
Maintainer-email: klaas.hoekstra94@gmail.com
License: MIT License
Project-URL: Homepage, https://github.com/klaashoekstra94/heishamon-rules-minify
Project-URL: documentation, https://github.com/denkiwakame/heishamon-rules-minify
Project-URL: repository, https://github.com/denkiwakame/heishamon-rules-minify
Keywords: package,setuptools
Classifier: License :: OSI Approved :: MIT License
Classifier: Programming Language :: Python
Requires-Python: >=3.7
License-File: LICENSE
Requires-Dist: requests
Provides-Extra: dev
Requires-Dist: pytest>=5.0.0; extra == "dev"
Requires-Dist: pytest-cov[all]; extra == "dev"
Requires-Dist: mypy>=0.910; extra == "dev"
Requires-Dist: black>=21.10b0; extra == "dev"
